arg_ranker/__init__.py
arg_ranker/__main__.py
arg_ranker/bin/.DS_Store
arg_ranker/bin/ARG_table.sum.py
arg_ranker/bin/Extract.MG.py
arg_ranker/bin/Filter.MG.py
arg_ranker/data/.DS_Store
arg_ranker/data/ARG_rank.txt
arg_ranker/data/SARG.db.fasta
arg_ranker/data/SARG.db.fasta.length
arg_ranker/data/SARG.structure.txt
arg_ranker/data/all_KO30.pro.fasta
arg_ranker/data/all_KO30.pro.fasta.length
arg_ranker/data/all_KO30_name.list
arg_ranker/example/.DS_Store
arg_ranker/example/EsCo_genome.fasta
arg_ranker/example/WEE300_all-trimmed-decont_1.fastq.zip
arg_ranker/example/metadata.txt
arg_ranker-3.7.2.dist-info/LICENSE.txt
arg_ranker-3.7.2.dist-info/METADATA
arg_ranker-3.7.2.dist-info/WHEEL
arg_ranker-3.7.2.dist-info/entry_points.txt
arg_ranker-3.7.2.dist-info/top_level.txt
arg_ranker-3.7.2.dist-info/RECORD
