Metadata-Version: 2.1
Name: arg-ranker
Version: 3.7.2
Summary: Ranking the risk of antibiotic resistance for genomes/metagenomes
Home-page: https://github.com/caozhichongchong/ARG_Ranker
Author: An-Ni Zhang
Author-email: anniz44@mit.edu
License: MIT
Keywords: antibiotic resistance,risk,one health,clinical AMR,mobile AMR
Platform: UNKNOWN
Classifier: Programming Language :: Python :: 3
Requires-Dist: pandas
Requires-Dist: argparse
Requires-Dist: glob2
Requires-Dist: statistics
Requires-Dist: biopython
